mciplayer/__init__.py
mciplayer/_mciwnd.pypy310-pp73-win_amd64.pyd
mciplayer/_mciwnd_unicode.pypy310-pp73-win_amd64.pyd
mciplayer/tool.py
mciplayer-2.0.2.dist-info/METADATA
mciplayer-2.0.2.dist-info/WHEEL
mciplayer-2.0.2.dist-info/entry_points.txt
mciplayer-2.0.2.dist-info/top_level.txt
mciplayer-2.0.2.dist-info/RECORD
