Metadata-Version: 2.1
Name: mciplayer
Version: 2.0.2
Summary: A simple audio player/recorder using MCI
